utilities/__init__.py
utilities/add_package.py
utilities/branching_funcs.py
utilities/db_funcs.py
utilities/files_system_funcs.py
utilities/fp_funcs.py
utilities/funcs.py
utilities/logs_handler.py
utilities/re_funcs.py
utilities/script_ui.py
utilities/ui_funcs.py
utilities/utils_funcs.py
utilities/yml_funcs.py
clemoni_utilities-1.3.6.dist-info/LICENSE
clemoni_utilities-1.3.6.dist-info/METADATA
clemoni_utilities-1.3.6.dist-info/WHEEL
clemoni_utilities-1.3.6.dist-info/top_level.txt
clemoni_utilities-1.3.6.dist-info/RECORD
