Metadata-Version: 2.1
Name: clemoni-utilities
Version: 1.3.6
Summary: A short utility library for Python
Home-page: https://github.com/clemoni/clemoni_utilities
Author: Clement Liscoet
Author-email: clement.liscoet@gmail.com
License: MIT
License-File: LICENSE
Requires-Dist: SQLAlchemy
Requires-Dist: mysql-connector-python
Requires-Dist: pymysql
Requires-Dist: pyyaml
